document_folder_structure/__init__.py
document_folder_structure/__main__.py
document_folder_structure/main.py
document_folder_structure-0.2.3.dist-info/licenses/LICENSE
document_folder_structure-0.2.3.dist-info/METADATA
document_folder_structure-0.2.3.dist-info/WHEEL
document_folder_structure-0.2.3.dist-info/entry_points.txt
document_folder_structure-0.2.3.dist-info/top_level.txt
document_folder_structure-0.2.3.dist-info/RECORD
