Metadata-Version: 2.4
Name: document-folder-structure
Version: 0.2.3
Summary: Automatic Markdown Documentation and Project Directory Tree Generator
Author-email: sdkng44 <sdkng44@gmail.com>
License-Expression: Apache-2.0
Project-URL: Homepage, https://github.com/sdkng44/document-folder-structure
Project-URL: Repository, https://github.com/sdkng44/document-folder-structure
Project-URL: Bug Tracker, https://github.com/sdkng44/document-folder-structure/issues
Keywords: directory-tree,markdown,documentation-generation,documentation-tool,repository-management,tree-structure,project-management
Classifier: Development Status :: 3 - Alpha
Classifier: Programming Language :: Python :: 3
Classifier: Operating System :: OS Independent
Classifier: Intended Audience :: Developers
Classifier: Topic :: Software Development :: Documentation
Requires-Python: >=3.6
License-File: LICENSE
Requires-Dist: openpyxl
Dynamic: license-file
